_pygeoapi_process/__init__.py
_pygeoapi_process/calc_agg_catalog.py
_pygeoapi_process/calc_weights_catalog.py
_pygeoapi_process/proc_test.py
_pygeoapi_process/proc_test_async.py
gdptools_pygeoapi_plugin-0.0.12.dist-info/LICENSE.md
gdptools_pygeoapi_plugin-0.0.12.dist-info/METADATA
gdptools_pygeoapi_plugin-0.0.12.dist-info/WHEEL
gdptools_pygeoapi_plugin-0.0.12.dist-info/entry_points.txt
gdptools_pygeoapi_plugin-0.0.12.dist-info/RECORD
