Metadata-Version: 2.3
Name: gdptools-pygeoapi-plugin
Version: 0.0.12
Summary: Gdptools Pygeoapi Plugin
License: LICENSE.md
Author: Richard McDonald
Author-email: rmcd@usgs.gov
Requires-Python: >=3.10,<3.13
Classifier: Development Status :: 1 - Planning
Classifier: License :: Other/Proprietary License
Classifier: Programming Language :: Python :: 3
Classifier: Programming Language :: Python :: 3.10
Classifier: Programming Language :: Python :: 3.11
Classifier: Programming Language :: Python :: 3.12
Classifier: Programming Language :: Python :: 3.13
Requires-Dist: gdptools (>0.2.15)
Requires-Dist: pygeoapi (>=0.14.0)
Requires-Dist: requests-toolbelt (>=1.0.0,<2.0.0)
Project-URL: Changelog, https://code.usgs.gov/wma/nhgf/toolsteam/gdptools-pygeoapi-plugin/releases
Project-URL: Documentation, https://gdptools-pygeoapi-plugin.readthedocs.io
Project-URL: Homepage, https://code.usgs.gov/wma/nhgf/toolsteam/gdptools-pygeoapi-plugin
Project-URL: Repository, https://code.usgs.gov/wma/nhgf/toolsteam/gdptools-pygeoapi-plugin
